MANIFEST.in
README.rst
setup.cfg
setup.py
fbmessage/__init__.py
fbmessage/constants.py
fbmessage/message.py
fbmessage.egg-info/PKG-INFO
fbmessage.egg-info/SOURCES.txt
fbmessage.egg-info/dependency_links.txt
fbmessage.egg-info/requires.txt
fbmessage.egg-info/top_level.txt