Metadata-Version: 1.1
Name: fbmessage
Version: 1.0.4
Summary: Integration with Facebook Messenger API
Home-page: https://github.com/wjdsupj/fbmessage
Author: agileboys.com
Author-email: agileboys@gmail.com
License: MIT
Keywords: facebook messenger message
Platform: UNKNOWN
Classifier: Development Status :: 5 - Production/Stable
Classifier: Intended Audience :: Education
Classifier: Intended Audience :: End Users/Desktop
Classifier: License :: Freeware
Classifier: Operating System :: POSIX
Classifier: Operating System :: Microsoft :: Windows
Classifier: Operating System :: MacOS :: MacOS X
Classifier: Topic :: Education
Classifier: Programming Language :: Python
Classifier: Programming Language :: Python :: 2.7
Classifier: Programming Language :: Python :: 3.4
Classifier: Programming Language :: Python :: 3.5
Classifier: Programming Language :: Python :: 3.6
